{
  "pier": "544",
  "loc": {
    "lon": "-88.528679",
    "lat": "42.550425",
    "geohash": "dp9416p6hq0",
    "pluscode": "HF2C+5GG Fontana-On-Geneva Lake, Wisconsin"
  },
  "property": {
    "association": "Sybil Lane Association",
    "established": "1914",
    "associationUrl": "",
    "tel": "",
    "address": {
      "street": "",
      "city": "Fontana",
      "state": "WI",
      "zip": "53125"
    }
  },
  "owners": [
    {
      "estateName": "",
      "member": false,
      "membershipType": "Residential Non-member",
      "members": [
        { "t": "", "f": "Sybil Lane Association", "m": "", "l": "", "s": "" }
      ]
    }
  ]
}
