{
  "pier": "644",
  "loc": {
    "longitude": -88.495917,
    "latitude": 42.560051
  },
  "property": {
    "association": "Wooddale Beach Association",
    "established": "1926",
    "associationUrl": "https://www.wooddalebeach.com/",
    "tel": "",
    "address": {
      "street": "",
      "city": "Lake Geneva",
      "state": "WI",
      "zip": "53147"
    },
    "business": "",
    "isMarina": 0,
    "hasFood": 0
  },
  "owners": [
    {
      "estateName": "",
      "member": false,
      "membershipType": "Residential Non-member",
      "members": [
        {
          "t": "",
          "f": "Wooddale Beach Assn. Pier",
          "m": "",
          "l": "",
          "s": "",
          "hidden": 0
        }
      ]
    },
    {
      "estateName": "",
      "member": true,
      "membershipType": "Regular",
      "members": [
        {
          "t": "",
          "f": "Fairbank",
          "m": "",
          "l": "Carpenter",
          "s": "",
          "hidden": 0
        },
        {
          "t": "",
          "f": "Lynne",
          "m": "",
          "l": "Carpenter",
          "s": "",
          "hidden": 0
        }
      ]
    },
    {
      "estateName": "",
      "member": true,
      "membershipType": "Regular",
      "members": [
        {
          "t": "",
          "f": "Eleanor",
          "m": "",
          "l": "Curtiss",
          "s": "",
          "hidden": 0
        }
      ]
    },
    {
      "estateName": "",
      "member": true,
      "membershipType": "Regular",
      "members": [
        {
          "t": "",
          "f": "Diane",
          "m": "",
          "l": "Fanelle",
          "s": "",
          "hidden": 0
        }
      ]
    },
    {
      "estateName": "",
      "member": true,
      "membershipType": "Regular",
      "members": [
        {
          "t": "",
          "f": "Jeff",
          "m": "",
          "l": "Jancik",
          "s": "",
          "hidden": 0
        }
      ]
    },
    {
      "estateName": "",
      "member": true,
      "membershipType": "Sustaining",
      "members": [
        {
          "t": "",
          "f": "Tricia",
          "m": "",
          "l": "McCoy",
          "s": "",
          "hidden": 0
        }
      ]
    },
    {
      "estateName": "",
      "member": true,
      "membershipType": "Regular",
      "members": [
        {
          "t": "",
          "f": "Mark",
          "m": "",
          "l": "Scharres",
          "s": "",
          "hidden": 0
        },
        {
          "t": "",
          "f": "Nancy",
          "m": "",
          "l": "McCoy",
          "s": "",
          "hidden": 0
        }
      ]
    },
    {
      "estateName": "",
      "member": true,
      "membershipType": "Contributing",
      "members": [
        {
          "t": "",
          "f": "Bill",
          "m": "",
          "l": "Thompson",
          "s": "",
          "hidden": 0
        },
        {
          "t": "",
          "f": "Diane",
          "m": "",
          "l": "Thompson",
          "s": "",
          "hidden": 0
        }
      ]
    },
    {
      "estateName": "",
      "member": true,
      "membershipType": "Regular",
      "members": [
        {
          "t": "",
          "f": "Sonette",
          "m": "",
          "l": "Tippens",
          "s": "",
          "hidden": 0
        }
      ]
    }
  ],
  "geohash": "dp9445z4r80",
  "pluscode": "HG63+2JG Williams Bay, Wisconsin",
  "public": 0,
  "bigSwimPier": 0
}