{
  "pier": "800",
  "loc": {
    "longitude": -88.44051,
    "latitude": 42.564815
  },
  "property": {
    "association": "",
    "established": "",
    "associationUrl": "",
    "tel": "",
    "address": {
      "street": "",
      "city": "Lake Geneva",
      "state": "WI",
      "zip": "53147"
    },
    "business": "",
    "isMarina": 0,
    "hasFood": 0
  },
  "owners": [
    {
      "estateName": "",
      "member": false,
      "membershipType": "Residential Non-member",
      "members": [
        {
          "t": "",
          "f": "Lance",
          "m": "",
          "l": "Champagne",
          "s": "",
          "hidden": 0
        },
        {
          "t": "",
          "f": "Susan",
          "m": "",
          "l": "Champagne",
          "s": "",
          "hidden": 0
        }
      ]
    }
  ],
  "geohash": "dp945kxw4b0",
  "pluscode": "HH75+WQH Lake Geneva, Wisconsin",
  "public": 0,
  "bigSwimPier": 0,
  "version": 1
}