{
  "pier": "043A",
  "loc": "-88.454634,42.579794",
  "property": {
    "association": "Shady Lane Pier Association",
    "established": "",
    "associationUrl": "",
    "tel": "",
    "address": {
      "street": "2481-2495 Forest Rest Ln",
      "city": "Lake Geneva",
      "state": "WI",
      "zip": "53147"
    },
    "business": "",
    "isMarina": 0,
    "hasFood": 0,
    "value": {
      "value": "",
      "source": "",
      "link": ""
    }
  },
  "owners": [
    {
      "estateName": "",
      "member": false,
      "membershipType": "Residential Non-member",
      "members": [
        {
          "t": "",
          "f": "Shady Lane Pier Association",
          "m": "",
          "l": "",
          "s": "",
          "hidden": 0
        }
      ]
    }
  ],
  "geohash": "dp945pmm380",
  "pluscode": "HGHW+W49 Lake Geneva, Wisconsin",
  "public": 0,
  "bigSwimPier": 0,
  "version": 1,
  "updatedOn": [
    "2025-10-17T03:31:30.758Z"
  ]
}