{
  "pier": "197",
  "loc": {
    "lon": "-88.527684",
    "lat": "42.566563",
    "geohash": "dp941t005q0",
    "pluscode": "HF8C+JWG Williams Bay, Wisconsin"
  },
  "property": {
    "association": "Cedar Point Park",
    "established": "1922",
    "associationUrl": "",
    "tel": "",
    "address": {
      "street": "270 Cir Pkwy",
      "city": "Williams Bay",
      "state": "WI",
      "zip": "53191"
    }
  },
  "owners": [
    {
      "estateName": "",
      "member": false,
      "membershipType": "Residential Non-member",
      "members": [
        { "t": "", "f": "Charles", "m": "W", "l": "Matthews", "s": "" }
      ]
    }
  ]
}
