{
  "pier": "130",
  "loc": {
    "longitude": -88.502247,
    "latitude": 42.57481
  },
  "property": {
    "association": "",
    "established": "",
    "associationUrl": "",
    "tel": "",
    "address": {
      "street": "W4101 Jerseyhurst Ln",
      "city": "Lake Geneva",
      "state": "WI",
      "zip": "53147"
    }
  },
  "owners": [
    {
      "estateName": "",
      "member": false,
      "membershipType": "Residential Non-member",
      "members": [
        {
          "t": "",
          "f": "Ignas",
          "m": "",
          "l": "Labanauskas",
          "s": "",
          "hidden": 0
        },
        {
          "t": "",
          "f": "Maureen",
          "m": "",
          "l": "Labanauskas",
          "s": "",
          "hidden": 0
        }
      ]
    }
  ],
  "geohash": "dp944nd8hp0",
  "pluscode": "HFFX+W4C Williams Bay, Wisconsin"
}